odoo8_addon_web_switch_company_warning-8.0.0.1.0.99.dev20-py2.7-nspkg.pth
odoo8_addon_web_switch_company_warning-8.0.0.1.0.99.dev20.dist-info/METADATA
odoo8_addon_web_switch_company_warning-8.0.0.1.0.99.dev20.dist-info/RECORD
odoo8_addon_web_switch_company_warning-8.0.0.1.0.99.dev20.dist-info/WHEEL
odoo8_addon_web_switch_company_warning-8.0.0.1.0.99.dev20.dist-info/namespace_packages.txt
odoo8_addon_web_switch_company_warning-8.0.0.1.0.99.dev20.dist-info/top_level.txt
odoo_addons/web_switch_company_warning/README.rst
odoo_addons/web_switch_company_warning/__init__.py
odoo_addons/web_switch_company_warning/__openerp__.py
odoo_addons/web_switch_company_warning/i18n/ar.po
odoo_addons/web_switch_company_warning/i18n/de.po
odoo_addons/web_switch_company_warning/i18n/es.po
odoo_addons/web_switch_company_warning/i18n/fi.po
odoo_addons/web_switch_company_warning/i18n/fr.po
odoo_addons/web_switch_company_warning/i18n/it.po
odoo_addons/web_switch_company_warning/i18n/pt_BR.po
odoo_addons/web_switch_company_warning/i18n/sl.po
odoo_addons/web_switch_company_warning/i18n/tr.po
odoo_addons/web_switch_company_warning/i18n/web_switch_company_warning.pot
odoo_addons/web_switch_company_warning/static/description/icon.png
odoo_addons/web_switch_company_warning/static/src/js/switch_company_warning.js
odoo_addons/web_switch_company_warning/static/src/js/switch_company_warning_worker.js
odoo_addons/web_switch_company_warning/static/src/xml/switch_company_warning.xml
odoo_addons/web_switch_company_warning/view/view.xml
